README.md
setup.py
src/catiacom/__init__.py
src/catiacom/catsession.py
src/catiacom/test_mod.py
src/catiacom.egg-info/PKG-INFO
src/catiacom.egg-info/SOURCES.txt
src/catiacom.egg-info/dependency_links.txt
src/catiacom.egg-info/requires.txt
src/catiacom.egg-info/top_level.txt
src/catiacom/catbase/__init__.py
src/catiacom/catbase/client.py
src/catiacom/docserv/__init__.py
src/catiacom/docserv/catdoc.py
src/catiacom/docserv/catpart.py
src/catiacom/docserv/catprod.py