Metadata-Version: 2.1
Name: catiacom
Version: 0.0.1
Summary: A catiacom python project
Home-page: https://github.com/pipelineinc/cv5com
Author: dev d
Author-email: dev@gmx.us
License: UNKNOWN
Project-URL: Bug Reports, https://github.com/pipelineinc/cv5com/issues
Project-URL: Funding, https://donate.pypi.org
Project-URL: Say Thanks!, https://saythanks.io/to/whatDdev
Project-URL: Source, https://github.com/pypa/catiacom/
Keywords: catia,cad,development,caa,geometry,rade,dassault,3dx,3dexperience
Platform: UNKNOWN
Classifier: Development Status :: 3 - Alpha
Classifier: Intended Audience :: Developers
Classifier: Topic :: Software Development :: Build Tools
Classifier: License :: OSI Approved :: MIT License
Classifier: Programming Language :: Python :: 3
Classifier: Programming Language :: Python :: 3.7
Classifier: Programming Language :: Python :: 3.8
Classifier: Programming Language :: Python :: 3.9
Classifier: Programming Language :: Python :: 3.10
Classifier: Programming Language :: Python :: 3 :: Only
Requires-Python: >=3.7, <4
Provides-Extra: dev
Provides-Extra: test
